README.md
setup.py
src/__init__.py
src/__main__.py
src/apiclient.py
src/configurator.py
src/converter.py
src/filedto.py
src/filereader.py
src/importer.py
src/minioreader.py
src/parser.py
src/rabbitmq.py
src/reader.py
src/../connection_config.ini
testgear_importer_allure.egg-info/PKG-INFO
testgear_importer_allure.egg-info/SOURCES.txt
testgear_importer_allure.egg-info/dependency_links.txt
testgear_importer_allure.egg-info/entry_points.txt
testgear_importer_allure.egg-info/requires.txt
testgear_importer_allure.egg-info/top_level.txt