Metadata-Version: 2.1
Name: testgear-importer-allure
Version: 1.3.2
Summary: Allure report importer for TestGear
Home-page: https://pypi.org/project/testgear-importer-allure/
Author: Integration team
License: Apache-2.0
Classifier: Programming Language :: Python :: 3
Classifier: Programming Language :: Python :: 3.6
Classifier: Programming Language :: Python :: 3.7
Classifier: Programming Language :: Python :: 3.8
Classifier: Programming Language :: Python :: 3.9
